os_grid_reference/__init__.py
os_grid_reference/constants.py
os_grid_reference/ngr_decode.py
os_grid_reference/ngr_encode.py
os_grid_reference-0.4.0.dist-info/LICENSE
os_grid_reference-0.4.0.dist-info/METADATA
os_grid_reference-0.4.0.dist-info/WHEEL
os_grid_reference-0.4.0.dist-info/top_level.txt
os_grid_reference-0.4.0.dist-info/RECORD
