Metadata-Version: 2.1
Name: os-grid-reference
Version: 0.4.0
Summary: Encode and decode British National Grid References
Home-page: https://gitlab.com/jbrobertson/os-grid-reference
Author: JB Robertson
Author-email: jbr@freeshell.org
License: UNKNOWN
Platform: UNKNOWN
Classifier: Programming Language :: Python :: 3
Classifier: License :: OSI Approved :: MIT License
Classifier: Operating System :: OS Independent
Requires-Python: >=3.6
